pretty_simple_namespace/__init__.py
pretty_simple_namespace/_vendor/__init__.py
pretty_simple_namespace/_vendor/all_purpose_dict/__init__.py
pretty_simple_namespace/_vendor/all_purpose_dict/_vendor/__init__.py
pretty_simple_namespace/_vendor/all_purpose_dict/_vendor/ordered_set-3.1.1-py3.7.egg-info/PKG-INFO
pretty_simple_namespace/_vendor/all_purpose_dict/_vendor/ordered_set-3.1.1-py3.7.egg-info/SOURCES.txt
pretty_simple_namespace/_vendor/all_purpose_dict/_vendor/ordered_set-3.1.1-py3.7.egg-info/dependency_links.txt
pretty_simple_namespace/_vendor/all_purpose_dict/_vendor/ordered_set-3.1.1-py3.7.egg-info/installed-files.txt
pretty_simple_namespace/_vendor/all_purpose_dict/_vendor/ordered_set-3.1.1-py3.7.egg-info/top_level.txt
pretty_simple_namespace/_vendor/all_purpose_dict/_vendor/ordered_set.py
pretty_simple_namespace/_vendor/all_purpose_dict/_vendor/tedent/__init__.py
pretty_simple_namespace/_vendor/all_purpose_dict/_vendor/tedent/_vendor/__init__.py
pretty_simple_namespace/_vendor/all_purpose_dict/_vendor/tedent/_vendor/ordered_set-3.1.1-py3.7.egg-info/PKG-INFO
pretty_simple_namespace/_vendor/all_purpose_dict/_vendor/tedent/_vendor/ordered_set-3.1.1-py3.7.egg-info/SOURCES.txt
pretty_simple_namespace/_vendor/all_purpose_dict/_vendor/tedent/_vendor/ordered_set-3.1.1-py3.7.egg-info/dependency_links.txt
pretty_simple_namespace/_vendor/all_purpose_dict/_vendor/tedent/_vendor/ordered_set-3.1.1-py3.7.egg-info/installed-files.txt
pretty_simple_namespace/_vendor/all_purpose_dict/_vendor/tedent/_vendor/ordered_set-3.1.1-py3.7.egg-info/top_level.txt
pretty_simple_namespace/_vendor/all_purpose_dict/_vendor/tedent/_vendor/ordered_set.py
pretty_simple_namespace/_vendor/all_purpose_dict/_vendor/tedent/_vendor/wrapt/__init__.py
pretty_simple_namespace/_vendor/all_purpose_dict/_vendor/tedent/_vendor/wrapt/_wrappers.cpython-37m-x86_64-linux-gnu.so
pretty_simple_namespace/_vendor/all_purpose_dict/_vendor/tedent/_vendor/wrapt/decorators.py
pretty_simple_namespace/_vendor/all_purpose_dict/_vendor/tedent/_vendor/wrapt/importer.py
pretty_simple_namespace/_vendor/all_purpose_dict/_vendor/tedent/_vendor/wrapt/wrappers.py
pretty_simple_namespace/_vendor/all_purpose_dict/_vendor/tedent/_vendor/wrapt-1.11.1.dist-info/INSTALLER
pretty_simple_namespace/_vendor/all_purpose_dict/_vendor/tedent/_vendor/wrapt-1.11.1.dist-info/LICENSE
pretty_simple_namespace/_vendor/all_purpose_dict/_vendor/tedent/_vendor/wrapt-1.11.1.dist-info/METADATA
pretty_simple_namespace/_vendor/all_purpose_dict/_vendor/tedent/_vendor/wrapt-1.11.1.dist-info/RECORD
pretty_simple_namespace/_vendor/all_purpose_dict/_vendor/tedent/_vendor/wrapt-1.11.1.dist-info/WHEEL
pretty_simple_namespace/_vendor/all_purpose_dict/_vendor/tedent/_vendor/wrapt-1.11.1.dist-info/top_level.txt
pretty_simple_namespace/_vendor/all_purpose_dict/_vendor/tedent/fns/__init__.py
pretty_simple_namespace/_vendor/all_purpose_dict/_vendor/tedent/fns/all_.py
pretty_simple_namespace/_vendor/all_purpose_dict/_vendor/tedent/fns/decorators/__init__.py
pretty_simple_namespace/_vendor/all_purpose_dict/_vendor/tedent/fns/decorators/argIsCallable.py
pretty_simple_namespace/_vendor/all_purpose_dict/_vendor/tedent/fns/decorators/argIsClass.py
pretty_simple_namespace/_vendor/all_purpose_dict/_vendor/tedent/fns/decorators/argIsListOfType.py
pretty_simple_namespace/_vendor/all_purpose_dict/_vendor/tedent/fns/decorators/argIsType.py
pretty_simple_namespace/_vendor/all_purpose_dict/_vendor/tedent/fns/discardFirst.py
pretty_simple_namespace/_vendor/all_purpose_dict/_vendor/tedent/fns/discardLastWhile.py
pretty_simple_namespace/_vendor/all_purpose_dict/_vendor/tedent/fns/forEach.py
pretty_simple_namespace/_vendor/all_purpose_dict/_vendor/tedent/fns/iif.py
pretty_simple_namespace/_vendor/all_purpose_dict/_vendor/tedent-0.1.5.dist-info/INSTALLER
pretty_simple_namespace/_vendor/all_purpose_dict/_vendor/tedent-0.1.5.dist-info/METADATA
pretty_simple_namespace/_vendor/all_purpose_dict/_vendor/tedent-0.1.5.dist-info/RECORD
pretty_simple_namespace/_vendor/all_purpose_dict/_vendor/tedent-0.1.5.dist-info/WHEEL
pretty_simple_namespace/_vendor/all_purpose_dict/_vendor/tedent-0.1.5.dist-info/top_level.txt
pretty_simple_namespace/_vendor/all_purpose_dict/_vendor/wrapt-1.10.11.dist-info/INSTALLER
pretty_simple_namespace/_vendor/all_purpose_dict/_vendor/wrapt-1.10.11.dist-info/LICENSE
pretty_simple_namespace/_vendor/all_purpose_dict/_vendor/wrapt-1.10.11.dist-info/METADATA
pretty_simple_namespace/_vendor/all_purpose_dict/_vendor/wrapt-1.10.11.dist-info/RECORD
pretty_simple_namespace/_vendor/all_purpose_dict/_vendor/wrapt-1.10.11.dist-info/WHEEL
pretty_simple_namespace/_vendor/all_purpose_dict/_vendor/wrapt-1.10.11.dist-info/top_level.txt
pretty_simple_namespace/_vendor/all_purpose_dict-0.2.4.dist-info/INSTALLER
pretty_simple_namespace/_vendor/all_purpose_dict-0.2.4.dist-info/METADATA
pretty_simple_namespace/_vendor/all_purpose_dict-0.2.4.dist-info/RECORD
pretty_simple_namespace/_vendor/all_purpose_dict-0.2.4.dist-info/WHEEL
pretty_simple_namespace/_vendor/all_purpose_dict-0.2.4.dist-info/top_level.txt
pretty_simple_namespace/_vendor/all_purpose_set/_vendor/ordered_set-3.1.1-py3.7.egg-info/PKG-INFO
pretty_simple_namespace/_vendor/all_purpose_set/_vendor/ordered_set-3.1.1-py3.7.egg-info/SOURCES.txt
pretty_simple_namespace/_vendor/all_purpose_set/_vendor/ordered_set-3.1.1-py3.7.egg-info/dependency_links.txt
pretty_simple_namespace/_vendor/all_purpose_set/_vendor/ordered_set-3.1.1-py3.7.egg-info/installed-files.txt
pretty_simple_namespace/_vendor/all_purpose_set/_vendor/ordered_set-3.1.1-py3.7.egg-info/top_level.txt
pretty_simple_namespace/_vendor/all_purpose_set/_vendor/tedent/_vendor/ordered_set-3.1.1-py3.7.egg-info/PKG-INFO
pretty_simple_namespace/_vendor/all_purpose_set/_vendor/tedent/_vendor/ordered_set-3.1.1-py3.7.egg-info/SOURCES.txt
pretty_simple_namespace/_vendor/all_purpose_set/_vendor/tedent/_vendor/ordered_set-3.1.1-py3.7.egg-info/dependency_links.txt
