Metadata-Version: 2.1
Name: pretty-simple-namespace
Version: 0.1.1
Summary: A pretty printer for SimpleNamespace
Home-page: https://github.com/olsonpm/py_pretty-simple-namespace
Author: Philip Olson
Author-email: philip.olson@pm.me
Requires-Python: >=3.7,<4.0
Classifier: Programming Language :: Python :: 3
Classifier: Programming Language :: Python :: 3.7
Project-URL: Repository, https://github.com/olsonpm/py_pretty-simple-namespace
